Metadata-Version: 1.1
Name: bendercito
Version: 0.4
Summary: Change your Slack status from command-line.
Home-page: https://github.com/quiqueporta/bendercito
Author: Quique Porta
Author-email: quiqueporta@gmail.com
License: MIT
Download-URL: https://github.com/quiqueporta/bendercito/releases
Platform: UNKNOWN
Classifier: Development Status :: 4 - Beta
Classifier: Environment :: Console
Classifier: Intended Audience :: Developers
Classifier: License :: OSI Approved :: MIT License
Classifier: Operating System :: OS Independent
Classifier: Programming Language :: Python
Classifier: Topic :: Utilities
